ipaddresstools/__init__.py
ipaddresstools/ipaddresstools.py
ipaddresstools/version.py
ipaddresstools-1.2.12.dist-info/LICENSE
ipaddresstools-1.2.12.dist-info/METADATA
ipaddresstools-1.2.12.dist-info/WHEEL
ipaddresstools-1.2.12.dist-info/top_level.txt
ipaddresstools-1.2.12.dist-info/RECORD
