Metadata-Version: 2.1
Name: ipaddresstools
Version: 1.2.12
Summary: This is a library used to manipulate and verify ipv4 address's. ucast and mcast
Home-page: https://ipaddresstools.readthedocs.io
Author: Benjamin P. Trachtenberg
Author-email: e_ben_75-python@yahoo.com
License: The MIT License (MIT)
Project-URL: Documentation, https://ipaddresstools.readthedocs.io/en/latest/
Project-URL: Source, https://github.com/btr1975/ipaddresstools
Project-URL: Tracker, https://github.com/btr1975/ipaddresstools/issues
Keywords: ipv4 ip multicast unicast network engineer
Platform: UNKNOWN
Classifier: Development Status :: 5 - Production/Stable
Classifier: License :: OSI Approved :: MIT License
Classifier: Intended Audience :: Developers
Classifier: Natural Language :: English
Classifier: Operating System :: MacOS :: MacOS X
Classifier: Operating System :: POSIX
Classifier: Operating System :: POSIX :: BSD
Classifier: Operating System :: POSIX :: Linux
Classifier: Operating System :: Microsoft :: Windows
Classifier: Programming Language :: Python :: 3
Classifier: Programming Language :: Python :: 3 :: Only
Classifier: Programming Language :: Python :: 3.6
Classifier: Programming Language :: Python :: 3.7
Classifier: Programming Language :: Python :: 3.8
Requires-Python: >=3.6
